Metadata-Version: 2.1
Name: bitmap2
Version: 0.2.4
Summary: An updated version of the bitmap library from https://github.com/wanji/bitmap
Home-page: https://github.com/wbarnha/bitmap
Author: wbarnha
Author-email: williambbarnhart@gmail.com
License: LICENSE.txt
Classifier: Programming Language :: Python :: 2.7
Classifier: Programming Language :: Python :: 3
Classifier: Topic :: Utilities
Classifier: License :: OSI Approved :: MIT License
Classifier: Development Status :: 5 - Production/Stable
Classifier: Intended Audience :: Developers
License-File: LICENSE.md
